{
    "name": "Palau",
    "background": "After three decades as part of the UN Trust Territory of the Pacific under US administration, this westernmost cluster of the Caroline Islands opted for independence in 1978 rather than join the Federated States of Micronesia. A Compact of Free Association with the US was approved in 1986 but not ratified until 1993. It entered into force the following year when the islands gained independence.",
    "coordinates": "7 30 N, 134 30 E",
    "region": "Oceania",
    "total_area": "459 sq km",
    "land_area": "459 sq km",
    "water_area": "0 sq km",
    "land_boundary": "0 km",
    "neighbors": "Unknown",
    "climate": "tropical; hot and humid; wet season May to November",
    "coastline": "1,519 km",
    "natural_hazards": [
        "typhoons (June to December)"
    ],
    "terrain": "varying topography from the high, mountainous main island of Babelthuap to low, coral islands usually fringed by large barrier reefs",
    "population_distribution": "most of the population is located on the southern end of the main island of Babelthuap",
    "natural_resources": [
        "forests",
        "minerals (especially gold)",
        "marine products",
        "deep-seabed minerals"
    ],
    "population": "21,685",
    "nationality": "Palauan(s)",
    "ethnic_groups": {
        "Palauan": "73%",
        "Carolinian": "2%",
        "Asian": "21.7%",
        "caucasian": "1.2%",
        "other": "2.1%"
    },
    "languages": {
        "Palauan (official)": "65.2%",
        "other Micronesian": "1.9%",
        "English (official)": "19.1%",
        "Filipino": "9.9%",
        "Chinese": "1.2%",
        "other": "2.8%"
    },
    "religions": {
        "Roman Catholic": "45.3%",
        "Protestant": "34.9%",
        "Modekngei": "5.7%",
        "Muslim": "3%",
        "Mormon": "1.5%",
        "other": "9.7%"
    },
    "government_type": "presidential republic in free association with the US",
    "national_symbols": "bai (native meeting house)",
    "national_colors": [
        "blue",
        "yellow"
    ],
    "gdp": "$0.292 billion",
    "agriculture": [
        "coconuts",
        "cassava",
        "sweet potatoes",
        "fish",
        "pigs",
        "chickens",
        "eggs",
        "bananas",
        "papaya",
        "breadfruit",
        "calamansi",
        "soursop",
        "Polynesian chestnuts",
        "Polynesian almonds",
        "mangoes",
        "taro",
        "guava",
        "beans",
        "cucumbers",
        "squash/pumpkins",
        "eggplant",
        "green onions",
        "kangkong",
        "cabbages",
        "radishes",
        "betel nuts",
        "melons",
        "peppers",
        "noni",
        "okra"
    ],
    "industries": [
        "tourism",
        "fishing",
        "subsistence agriculture"
    ],
    "exports": [
        "shellfish",
        "tuna",
        "other fish (many species)"
    ],
    "imports": [
        "machinery and equipment",
        "fuels",
        "metals",
        "foodstuffs"
    ],
    "broadband_subscriptions": "Unknown",
    "internet_users": "7,650",
    "mobile_subscriptions": "24,000",
    "internet_country_code": ".pw",
    "military_and_security_forces": "no regular military forces; the Ministry of Justice includes divisions/bureaus for public security, police functions, and maritime law enforcement.",
    "percent_GDP_on_military": "Unknown",
    "pipelines": [
        "Unknown"
    ],
    "ports_and_terminals": {
        "major seaport(s)": "Koror"
    },
    "waterways": "Unknown",
    "number_of_airports": "3",
    "international_disputes": "maritime delineation negotiations continue with Philippines, Indonesia",
    "terrorism": "Unknown"
}